setup.py
ppp_core/__init__.py
ppp_core/__main__.py
ppp_core/config.py
ppp_core/exceptions.py
ppp_core/router.py
ppp_core/verbose_log.py
ppp_core.egg-info/PKG-INFO
ppp_core.egg-info/SOURCES.txt
ppp_core.egg-info/dependency_links.txt
ppp_core.egg-info/requires.txt
ppp_core.egg-info/top_level.txt